check_updates/__init__.py
check_updates/__main__.py
check_updates/_version.py
check_updates/main.py
check_updates/poetry.py
check_updates/pre_commit.py
check_updates/py.typed
check_updates/pypi.py
check_updates/update.py
py_check_updates-0.1.1.dist-info/entry_points.txt
py_check_updates-0.1.1.dist-info/LICENSE
py_check_updates-0.1.1.dist-info/WHEEL
py_check_updates-0.1.1.dist-info/METADATA
py_check_updates-0.1.1.dist-info/RECORD
