Metadata-Version: 2.1
Name: py-check-updates
Version: 0.1.1
Summary: A Python dependency update checker.
Home-page: https://github.com/tueda/py-check-updates
License: MIT
Keywords: check,updates,dependencies,version
Author: Takahiro Ueda
Author-email: takahiro.ueda@yahoo.com
Requires-Python: >=3.7,<4.0
Classifier: Development Status :: 4 - Beta
Classifier: Intended Audience :: Developers
Classifier: License :: OSI Approved :: MIT License
Classifier: Programming Language :: Python :: 3
Classifier: Programming Language :: Python :: 3.10
Classifier: Programming Language :: Python :: 3.7
Classifier: Programming Language :: Python :: 3.8
Classifier: Programming Language :: Python :: 3.9
Classifier: Topic :: Software Development
Classifier: Topic :: Utilities
Requires-Dist: PyYAML (>=6.0,<7.0)
Requires-Dist: importlib-metadata (>=1.4); python_version < "3.8"
Requires-Dist: requests (>=2.28.1,<3.0.0)
Requires-Dist: tomlkit (>=0.11.0,<0.12.0)
Project-URL: Repository, https://github.com/tueda/py-check-updates
